red_magic/__init__.py
red_magic/chi2.py
red_magic/general.py
red_magic/graphic_selection.py
red_magic/manual_fitting.py
red_magic/mcmc_addon.py
red_magic/model_physics.py
red_magic/psd.py
red_magic/stream_reader.py
red_magic-0.0.11.dist-info/LICENSE
red_magic-0.0.11.dist-info/METADATA
red_magic-0.0.11.dist-info/WHEEL
red_magic-0.0.11.dist-info/top_level.txt
red_magic-0.0.11.dist-info/RECORD
