Metadata-Version: 2.1
Name: red-magic
Version: 0.0.11
Summary: Generic analysis and processing tools for Manoir.
Home-page: https://git.ipnl.in2p3.fr/manoir/red_magic
Author: Dimitri Misiak
Author-email: dimitrimisiak@gmail.com
License: UNKNOWN
Platform: UNKNOWN
Classifier: Programming Language :: Python :: 3
Classifier: License :: OSI Approved :: MIT License
Classifier: Operating System :: OS Independent
Requires-Python: >=3.6
Requires-Dist: numpy
Requires-Dist: scipy
Requires-Dist: matplotlib
Requires-Dist: tqdm
Requires-Dist: uproot
